setup.py
django_ts_router/__init__.py
django_ts_router/apps.py
django_ts_router/route.py
django_ts_router/tsc.py
django_ts_router/urls.py
django_ts_router/views.py
django_ts_router.egg-info/PKG-INFO
django_ts_router.egg-info/SOURCES.txt
django_ts_router.egg-info/dependency_links.txt
django_ts_router.egg-info/top_level.txt
django_ts_router/management/__init__.py
django_ts_router/management/commands/__init__.py
django_ts_router/management/commands/export_ts_router.py
django_ts_router/templates/django_ts_router/router.ts.tmpl