Metadata-Version: 1.1
Name: django-ts-router
Version: 0.7.2
Summary: Generates a TypeScript (or JavaScript) source code that includes URL reverse functions for your Django app.
Home-page: https://github.com/strippers/django-ts-router
Author: Tomohiro Otsuka
Author-email: t.otsuka@gmail.com
License: LGPL
Keywords: django,javascript,typescript,routing,url
Platform: UNKNOWN
Classifier: Development Status :: 4 - Beta
Classifier: Environment :: Web Environment
Classifier: Framework :: Django :: 1.8
Classifier: Framework :: Django :: 1.9
Classifier: Intended Audience :: Developers
Classifier: License :: OSI Approved :: GNU Lesser General Public License v2 or later (LGPLv2+)
Classifier: Operating System :: OS Independent
Classifier: Programming Language :: Python :: 3.4
Classifier: Programming Language :: Python :: 3.5
Classifier: Topic :: Internet :: WWW/HTTP
